imb/__init__.py
imb/base.py
imb/onnx.py
imb/triton.py
imb-1.0.3.dist-info/LICENSE
imb-1.0.3.dist-info/METADATA
imb-1.0.3.dist-info/WHEEL
imb-1.0.3.dist-info/top_level.txt
imb-1.0.3.dist-info/RECORD
