Metadata-Version: 2.1
Name: imb
Version: 1.0.3
Summary: Python library for run inference of deep learning models in different backends
Home-page: https://github.com/TheConstant3/InferenceMultiBackend
Author: p-constant
Author-email: nikshorop@gmail.com
License: UNKNOWN
Platform: UNKNOWN
Classifier: Programming Language :: Python :: 3.8
Classifier: License :: OSI Approved :: MIT License
Classifier: Operating System :: OS Independent
Requires-Python: >=3.8
License-File: LICENSE
Requires-Dist: numpy
Provides-Extra: all
Requires-Dist: tritonclient[all]>=2.38.0; extra == "all"
Requires-Dist: onnxruntime>=1.16.0; extra == "all"
Requires-Dist: onnxruntime-gpu>=1.16.0; extra == "all"
Provides-Extra: onnxcpu
Requires-Dist: onnxruntime>=1.16.0; extra == "onnxcpu"
Provides-Extra: onnxgpu
Requires-Dist: onnxruntime-gpu>=1.16.0; extra == "onnxgpu"
Provides-Extra: triton
Requires-Dist: tritonclient[all]>=2.38.0; extra == "triton"
